{
    "HTML": [
        "https://mariadb.com/kb/en/dec-numeric-fixed/"
    ],
    "Title": [
        "DEC, NUMERIC, FIXED"
    ],
    "Feature": [
        "DEC[(M[,D])] [SIGNED | UNSIGNED | ZEROFILL]\n\nNUMERIC[(M[,D])] [SIGNED | UNSIGNED | ZEROFILL]\n\nFIXED[(M[,D])] [SIGNED | UNSIGNED | ZEROFILL]\n"
    ],
    "Description": [
        "These types are synonyms for DECIMAL. The FIXED synonym is\navailable for compatibility with other database systems."
    ],
    "Examples": [],
    "Category": [
        "Numeric Data Types"
    ]
}