{
    "HTML": [
        "https://www.postgresql.org/docs/current/functions-json.html"
    ],
    "Title": [
        "value . decimal"
    ],
    "Feature": [
        "value . decimal( [ precision [ , scale ] ] ) → decimal"
    ],
    "Description": [
        "Rounded decimal value converted from a JSON number or string (precision and scale must be integer values)"
    ],
    "Examples": [
        "jsonb_path_query('1234.5678', '$.decimal(6, 2)') → 1234.57"
    ],
    "Category": [
        "JSON Functions and Operators"
    ]
}