{
    "HTML": [
        "https://mariadb.com//kb/en/json_extract/"
    ],
    "Title": [
        "JSON_EXTRACT"
    ],
    "Feature": [
        "JSON_EXTRACT(json_doc, path[, path] ...)\n"
    ],
    "Description": [
        "Extracts data from a JSON document. The extracted data is selected from the parts matching the path arguments. Returns all matched values; either as a single matched value, or, if the arguments could return multiple values, a result autowrapped as an array in the matching order.",
        "Returns NULL if no paths match or if any of the arguments are NULL. ",
        "An error will occur if any path argument is not a valid path, or if the json_doc argument is not a valid JSON document.",
        "The path expression be a JSONPath expression as supported by MariaDB "
    ],
    "Examples": [
        "SELECT JSON_EXTRACT(@json, '$[1]');",
        "SELECT JSON_EXTRACT(@json, '$[2]');",
        "SELECT JSON_EXTRACT(@json, '$[2][1]');"
    ],
    "Category": [
        "JSON Functions"
    ]
}