{
    "HTML": "https://mariadb.com//kb/en/is_ipv6/",
    "Title": "IS_IPV6",
    "Feature": [
        "IS_IPV6(expr)\n"
    ],
    "Description": [
        "Returns 1 if the expression is a valid IPv6 address specified as a string, otherwise returns 0. Does not consider IPv4 addresses to be valid IPv6 addresses."
    ],
    "Examples": [
        " SELECT IS_IPV6('48f3::d432:1431:ba23:846f');\n+--------------------------------------+\n| IS_IPV6('48f3::d432:1431:ba23:846f') |\n+--------------------------------------+\n|                                    1 |\n+--------------------------------------+\n1 row in set (0.02 sec)\n\nSELECT IS_IPV6('10.0.1.1');\n+---------------------+\n| IS_IPV6('10.0.1.1') |\n+---------------------+\n|                   0 |\n+---------------------+\n"
    ],
    "Category": [
        "Miscellaneous Functions"
    ],
    "Effective SQLs Refined": [
        "SELECT IS_IPV6('48f3::d432:1431:ba23:846f');"
    ],
    "Ineffective SQLs Refined": [
        "set (0.02 sec)\n\nSELECT IS_IPV6('10.0.1.1');"
    ],
    "Wrong Messages from Ineffective SQLs Refined": [
        "(pymysql.err.ProgrammingError) (1064, \"You have an error in your SQL syntax; check the manual that corresponds to your MariaDB server version for the right syntax to use near '(0.02 sec)\\n\\nSELECT IS_IPV6('10.0.1.1')' at line 1\")\n[SQL: set (0.02 sec)\n\nSELECT IS_IPV6('10.0.1.1');]\n(Background on this error at: https://sqlalche.me/e/20/f405)"
    ],
    "SQLs Generated1": [],
    "SQLs Generated Costs1": [],
    "SQLs Generated ExecResults1": [],
    "SQLs Generated ExecTimes1": [],
    "SQLs Generated ErrorMessages1": [],
    "Effective SQLs Generated1": [],
    "SQLs Generated2": [],
    "SQLs Generated Costs2": [],
    "SQLs Generated ExecResults2": [],
    "SQLs Generated ExecTimes2": [],
    "SQLs Generated ErrorMessages2": [],
    "Effective SQLs Generated2": []
}