{
    "HTML": [
        "https://www.oceanbase.com/docs/enterprise-oceanbase-database-cn-1000000000823336"
    ],
    "Title": [
        "LOG10"
    ],
    "Feature": [
        "LOG10(X)\n"
    ],
    "Description": [
        "返回以 10 为底的 X 的指数。"
    ],
    "Examples": [
        "obclient> SELECT LOG10(1000);\n+-------------+\n| LOG10(1000) |\n+-------------+\n|           3 |\n+-------------+\n1 row in set\n\nobclient> SELECT LOG10(-1000);\n+--------------+\n| LOG10(-1000) |\n+--------------+\n|         NULL |\n+--------------+\n1 row in set, 1 warning\n"
    ],
    "Category": [
        "Mathematical Functions"
    ]
}