{
    "HTML": [
        "https://duckdb.org/docs/sql/functions/timestamptz"
    ],
    "Title": [
        "make_timestamptz(bigint, bigint, bigint, bigint, bigint, double)"
    ],
    "Feature": [
        "make_timestamptz(bigint, bigint, bigint, bigint, bigint, double)"
    ],
    "Description": [
        "The TIMESTAMP WITH TIME ZONE for the given parts in the current time zone."
    ],
    "Examples": [
        "make_timestamptz(1992, 9, 20, 13, 34, 27.123456)"
    ],
    "Category": [
        "Timestamp with Time Zone Functions"
    ]
}