{
    "HTML": [
        "https://www.oceanbase.com/docs/enterprise-oceanbase-database-cn-1000000000823117"
    ],
    "Title": [
        "VSIZE"
    ],
    "Feature": [
        "VSIZE (expr)\n"
    ],
    "Description": [
        "该函数返回参数 expr 的大小（字节数）。",
        "expr 可以是数值数据类型（NUMBER、FLOAT、BINARY_FLOAT 或 BINARY_DOUBLE）或字符数据类型（ CHAR、VARCHAR2、NCHAR 或 NVARCHAR2）的值或表达式。",
        "返回一个 NUMBER 类型的值。",
        "如果 expr 为 NULL，则函数返回 NULL。"
    ],
    "Examples": [
        "obclient> SELECT VSIZE(123456),VSIZE('ABCDEF'),VSIZE ('中华人民共和国') FROM DUAL;\n+---------------+-----------------+--------------------------------+\n| VSIZE(123456) | VSIZE('ABCDEF') | VSIZE('中华人民共和国')        |\n+---------------+-----------------+--------------------------------+\n|             8 |               6 |                             21 |\n+---------------+-----------------+--------------------------------+\n1 row in set\n"
    ],
    "Category": [
        "Encoding and Decoding Functions"
    ]
}